ngocbienml/__init__.py
ngocbienml/config.py
ngocbienml/main.py
ngocbienml/data_processing/__init__.py
ngocbienml/data_processing/data_processing_.py
ngocbienml/metrics/__init__.py
ngocbienml/metrics/metrics_.py
ngocbienml/model/__init__.py
ngocbienml/model/model_.py
ngocbienml/model/model_with_pipeline.py
ngocbienml/pipeline/__init__.py
ngocbienml/pipeline/pipeline_.py
ngocbienml/research_cv/__init__.py
ngocbienml/research_cv/searchCv.py
ngocbienml/utils/__init__.py
ngocbienml/utils/config.py
ngocbienml/utils/data_generate.py
ngocbienml/utils/utils_.py
ngocbienml/visualization/__init__.py
ngocbienml/visualization/plot.py
ngocbienml-2.0.0.dist-info/LICENSE.md
ngocbienml-2.0.0.dist-info/METADATA
ngocbienml-2.0.0.dist-info/WHEEL
ngocbienml-2.0.0.dist-info/top_level.txt
ngocbienml-2.0.0.dist-info/RECORD
