Metadata-Version: 2.1
Name: ngocbienml
Version: 2.0.0
Summary: An ecosystem for machine learning project
Home-page: https://github.com/ngocbien/ngocbienml
Author: Nguyen Ngoc Bien
Author-email: ngocbien.nguyen.vn@gmail.com
License: MIT
Platform: UNKNOWN
Classifier: Programming Language :: Python :: 3
Classifier: License :: OSI Approved :: MIT License
Classifier: Operating System :: OS Independent
Requires-Python: >=3.6
Requires-Dist: numpy
Requires-Dist: scikit-learn
Requires-Dist: scipy
Requires-Dist: pandas
Requires-Dist: matplotlib
Requires-Dist: seaborn
